hookit/__init__.py
hookit/config.py
hookit/exc.py
hookit/hookit.py
hookit/http.py
hookit/log.py
hookit_python-1.0.0.dist-info/LICENSE
hookit_python-1.0.0.dist-info/METADATA
hookit_python-1.0.0.dist-info/WHEEL
hookit_python-1.0.0.dist-info/top_level.txt
hookit_python-1.0.0.dist-info/RECORD
